RUTTS/__init__.py
RUTTS/infer_onnx.py
RUTTS/tokenizer/__init__.py
RUTTS/tokenizer/g2p/__init__.py
RUTTS/tokenizer/g2p/g2p.py
RUTTS/tokenizer/g2p/tokenizer.py
RUTTS/tokenizer/gruut/__init__.py
RUTTS/tokenizer/gruut/tokenizer.py
RUTTS-0.1.13.dist-info/LICENSE.txt
RUTTS-0.1.13.dist-info/METADATA
RUTTS-0.1.13.dist-info/WHEEL
RUTTS-0.1.13.dist-info/top_level.txt
RUTTS-0.1.13.dist-info/RECORD
